[{"tecnologia":"GPON","uf":"AL","name":"Arapiraca, AL <br> GPON","longitude":"-36.661471","cidade":"Arapiraca","latitude":"-9.754866","color":"green"},{"tecnologia":"GPON","uf":"GO","name":"Trindade, GO <br> GPON","longitude":"-49.492667","cidade":"Trindade","latitude":"-16.651708","color":"green"},{"tecnologia":"GPON","uf":"MG","name":"Araxá, MG <br> GPON","longitude":"-46.943804","cidade":"Araxá","latitude":"-19.590176","color":"green"},{"tecnologia":"GPON","uf":"MG","name":"Itajubá, MG <br> GPON","longitude":"-45.459818","cidade":"Itajubá","latitude":"-22.422481","color":"green"},{"tecnologia":"GPON","uf":"RJ","name":"Paraíba Do Sul, RJ <br> GPON","longitude":"-43.304004","cidade":"Paraíba Do Sul","latitude":"-22.158462","color":"green"},{"tecnologia":"GPON","uf":"RO","name":"Ji-Paraná, RO <br> GPON","longitude":"-61.932152","cidade":"Ji-Paraná","latitude":"-10.877741","color":"green"},{"tecnologia":"GPON","uf":"RS","name":"Camaquã, RS <br> GPON","longitude":"-51.80431","cidade":"Camaquã","latitude":"-30.848897","color":"green"},{"tecnologia":"GPON","uf":"RS","name":"Dois Irmãos, RS <br> GPON","longitude":"-51.089776","cidade":"Dois Irmãos","latitude":"-29.58356","color":"green"},{"tecnologia":"GPON","uf":"RS","name":"Marau, RS <br> GPON","longitude":"-52.198625","cidade":"Marau","latitude":"-28.449754","color":"green"},{"tecnologia":"GPON","uf":"RS","name":"Vacaria, RS <br> GPON","longitude":"-50.941791","cidade":"Vacaria","latitude":"-28.507868","color":"green"},{"tecnologia":"GPON","uf":"SC","name":"Içara, SC <br> GPON","longitude":"-49.308654","cidade":"Içara","latitude":"-28.713206","color":"green"},{"tecnologia":"GPON","uf":"SP","name":"Agudos, SP <br> GPON","longitude":"-48.98632","cidade":"Agudos","latitude":"-22.469433","color":"green"},{"tecnologia":"GPON","uf":"SP","name":"Casa Branca, SP <br> GPON","longitude":"-47.085245","cidade":"Casa Branca","latitude":"-21.77081","color":"green"},{"tecnologia":"GPON","uf":"SP","name":"Ibaté, SP <br> GPON","longitude":"-47.988211","cidade":"Ibaté","latitude":"-21.958358","color":"green"},{"tecnologia":"GPON","uf":"SP","name":"Jaguariúna, SP <br> GPON","longitude":"-46.985062","cidade":"Jaguariúna","latitude":"-22.70374","color":"green"},{"tecnologia":"GPON","uf":"SP","name":"Piedade, SP <br> GPON","longitude":"-47.425572","cidade":"Piedade","latitude":"-23.713941","color":"green"},{"tecnologia":"GPON","uf":"SP","name":"Santa Cruz das Palmeiras, SP <br> GPON","longitude":"-47.248023","cidade":"Santa Cruz das Palmeiras","latitude":"-21.823475","color":"green"},{"tecnologia":"GPON","uf":"SP","name":"Tambaú, SP <br> GPON","longitude":"-47.270344","cidade":"Tambaú","latitude":"-21.70292","color":"green"},{"tecnologia":"GPON","uf":"TO","name":"Araguaína, TO <br> GPON","longitude":"-48.204402","cidade":"Araguaína","latitude":"-7.192375","color":"green"},{"tecnologia":"GPON","uf":"TO","name":"Gurupi, TO <br> GPON","longitude":"-49.068046","cidade":"Gurupi","latitude":"-11.72794","color":"green"},{"tecnologia":"GPON","uf":"PR","name":"Apucarana, PR <br> GPON","longitude":"-51.463486","cidade":"Apucarana","latitude":"-23.549961","color":"green"},{"tecnologia":"GPON","uf":"SC","name":"Guaramirim, SC <br> GPON","longitude":"-49.002628","cidade":"Guaramirim","latitude":"-26.468753","color":"green"},{"tecnologia":"GPON","uf":"SP","name":"Caieiras, SP <br> GPON","longitude":"-46.73974","cidade":"Caieiras","latitude":"-23.360729","color":"green"},{"tecnologia":"GPON","uf":"SP","name":"Itupeva, SP <br> GPON","longitude":"-47.059262","cidade":"Itupeva","latitude":"-23.152635","color":"green"},{"tecnologia":"GPON","uf":"SP","name":"Mairinque, SP <br> GPON","longitude":"-47.184995","cidade":"Mairinque","latitude":"-23.539822","color":"green"}]
